Metadata-Version: 2.1
Name: simple-range
Version: 0.0.3
Summary: Weka-inspired index range using human-readable 1-based indices and placeholders (eg first/last).
Home-page: https://github.com/wairas/simple-range
Author: Peter Reutemann
Author-email: fracpete@waikato.ac.nz
License: MIT License
Classifier: Development Status :: 4 - Beta
Classifier: License :: OSI Approved :: MIT License
Classifier: Topic :: Scientific/Engineering
Classifier: Programming Language :: Python :: 3
License-File: LICENSE
